sentinel_pii/__init__.py
sentinel_pii/faker_utils.py
sentinel_pii/redactor.py
sentinel_pii/utils.py
sentinel_pii_sdk-0.1.0.dist-info/METADATA
sentinel_pii_sdk-0.1.0.dist-info/WHEEL
sentinel_pii_sdk-0.1.0.dist-info/licenses/LICENSE
sentinel_pii_sdk-0.1.0.dist-info/RECORD
