Metadata-Version: 2.4
Name: sentinel-pii-sdk
Version: 0.1.0
Summary: Python SDK for Sentinel PII Redaction - State-of-the-art PII detection and redaction using fine-tuned Granite models
Project-URL: Homepage, https://huggingface.co/cernis-intelligence/sentinel
Project-URL: Repository, https://github.com/cernis-intelligence/sentinel-pii-sdk
Project-URL: Documentation, https://huggingface.co/cernis-intelligence/sentinel
Author-email: Cernis Intelligence <support@cernis.ai>
License: Apache-2.0
License-File: LICENSE
Keywords: granite,huggingface,nlp,pii,privacy,redaction
Classifier: Development Status :: 4 - Beta
Classifier: Intended Audience :: Developers
Classifier: License :: OSI Approved :: Apache Software License
Classifier: Programming Language :: Python :: 3
Classifier: Programming Language :: Python :: 3.9
Classifier: Programming Language :: Python :: 3.10
Classifier: Programming Language :: Python :: 3.11
Classifier: Programming Language :: Python :: 3.12
Classifier: Topic :: Scientific/Engineering :: Artificial Intelligence
Classifier: Topic :: Security
Requires-Python: >=3.9
Requires-Dist: accelerate>=0.20.0
Requires-Dist: torch>=2.0.0
Requires-Dist: tqdm>=4.65.0
Requires-Dist: transformers>=4.36.0
Provides-Extra: all
Requires-Dist: faker>=20.0.0; extra == 'all'
Provides-Extra: faker
Requires-Dist: faker>=20.0.0; extra == 'faker'
